{
  "orders": [
    {
      "id": "871122+6343",
      "orderNo": "008-69-1374",
      "date": 1663510764012,
      "orderItems": [
        {
          "id": "325-51-7735",
          "itemId": "PremiumCode241089",
          "itemName": "Mediocre Paper Shoes",
          "quantity": 2,
          "unitPrice": 33.52
        },
        {
          "id": "196-19-5021",
          "itemId": "PremiumCode813776",
          "itemName": "Intelligent Paper Lamp",
          "quantity": 1,
          "unitPrice": 53.98
        }
      ]
    },
    {
      "id": "490129-9521",
      "orderNo": "440-74-2873",
      "date": 1663510764036,
      "orderItems": [
        {
          "id": "873-35-5498",
          "itemId": "KillerPrice353577",
          "itemName": "Intelligent Linen Gloves",
          "quantity": 2,
          "unitPrice": 50.12
        },
        {
          "id": "733-12-7122",
          "itemId": "SpecialDiscount017637",
          "itemName": "Awesome Granite Bottle",
          "quantity": 1,
          "unitPrice": 18.92
        }
      ]
    }
  ]
}